library/__init__.py
library_bot_pp-0.3.dist-info/METADATA
library_bot_pp-0.3.dist-info/WHEEL
library_bot_pp-0.3.dist-info/entry_points.txt
library_bot_pp-0.3.dist-info/top_level.txt
library_bot_pp-0.3.dist-info/RECORD
