Metadata-Version: 2.1
Name: library-bot-pp
Version: 0.3
Summary: A library that creates a Python bot
Home-page: https://ppbot.web.app/mylibrary
Author: P
Author-email: parepare2154@gmail.com
